{"_type":"export","__export_format":4,"__export_date":"2020-02-04T14:11:28.730Z","__export_source":"insomnia.desktop.app:v7.0.5","resources":[{"_id":"req_d4c56ab8c55d43a89cd5f5ede0dab111","authentication":{"token":"{{token}}","type":"bearer"},"body":{},"created":1580543722114,"description":"","headers":[],"isPrivate":false,"metaSortKey":-1580543722114,"method":"GET","modified":1580543880508,"name":"/","parameters":[],"parentId":"fld_b29ca72012b74ab999a487cd6c430c10","settingDisableRenderRequestBody":false,"settingEncodeUrl":true,"settingFollowRedirects":"global","settingRebuildPath":true,"settingSendCookies":true,"settingStoreCookies":true,"url":"{{base}}/kelas","_type":"request"},{"_id":"fld_b29ca72012b74ab999a487cd6c430c10","created":1580543719061,"description":"","environment":{},"environmentPropertyOrder":null,"metaSortKey":-1580543719061,"modified":1580543719061,"name":"/kelas","parentId":"wrk_30de5e0761b847ac9dcff92e0168f43c","_type":"request_group"},{"_id":"wrk_30de5e0761b847ac9dcff92e0168f43c","created":1580540846898,"description":"","modified":1580540846898,"name":"athfal","parentId":null,"_type":"workspace"},{"_id":"req_b5118eb5d8014ef7923b889d238f71e6","authentication":{"token":"{{token}}","type":"bearer"},"body":{},"created":1580544237402,"description":"","headers":[],"isPrivate":false,"metaSortKey":-1580543722214,"method":"GET","modified":1580546032859,"name":"/getmapel","parameters":[],"parentId":"fld_c388dc23161848cc8e6660d445187719","settingDisableRenderRequestBody":false,"settingEncodeUrl":true,"settingFollowRedirects":"global","settingRebuildPath":true,"settingSendCookies":true,"settingStoreCookies":true,"url":"{{base}}/mapel/getmapel","_type":"request"},{"_id":"fld_c388dc23161848cc8e6660d445187719","created":1580544237400,"description":"","environment":{},"environmentPropertyOrder":null,"metaSortKey":-1580542328367,"modified":1580544245594,"name":"/mapel","parentId":"wrk_30de5e0761b847ac9dcff92e0168f43c","_type":"request_group"},{"_id":"req_e5e76a1235184ff1a06e925934991b70","authentication":{"token":"{{token}}","type":"bearer"},"body":{},"created":1580546283231,"description":"","headers":[],"isPrivate":false,"metaSortKey":-1580543722189,"method":"GET","modified":1580546290255,"name":"/detailmapel","parameters":[],"parentId":"fld_c388dc23161848cc8e6660d445187719","settingDisableRenderRequestBody":false,"settingEncodeUrl":true,"settingFollowRedirects":"global","settingRebuildPath":true,"settingSendCookies":true,"settingStoreCookies":true,"url":"{{base}}/mapel/getmapel","_type":"request"},{"_id":"req_227c60bc2c5845159da9691f31f04608","authentication":{"token":"{{token}}","type":"bearer"},"body":{},"created":1580545986749,"description":"","headers":[],"isPrivate":false,"metaSortKey":-1580543722164,"method":"GET","modified":1580546051398,"name":"/getmateri","parameters":[],"parentId":"fld_c388dc23161848cc8e6660d445187719","settingDisableRenderRequestBody":false,"settingEncodeUrl":true,"settingFollowRedirects":"global","settingRebuildPath":true,"settingSendCookies":true,"settingStoreCookies":true,"url":"{{base}}/mapel/getmateri","_type":"request"},{"_id":"req_fe301dfaa56344c6b690c3a51e78b12f","authentication":{},"body":{"mimeType":"application/x-www-form-urlencoded","params":[{"description":"","id":"pair_99c5d8b44f244f24914b7cd2d2e8628a","name":"username","value":"admin"},{"description":"","id":"pair_6a6b7deef89b452c829dbc82d620d82f","name":"password","value":"admin"}]},"created":1580540937673,"description":"","headers":[{"id":"pair_7ee34ebbaef0463fb041cbccced57e1e","name":"Content-Type","value":"application/x-www-form-urlencoded"}],"isPrivate":false,"metaSortKey":-1580540937673,"method":"POST","modified":1580540967290,"name":"/login","parameters":[],"parentId":"wrk_30de5e0761b847ac9dcff92e0168f43c","settingDisableRenderRequestBody":false,"settingEncodeUrl":true,"settingFollowRedirects":"global","settingRebuildPath":true,"settingSendCookies":true,"settingStoreCookies":true,"url":"{{base}}/login","_type":"request"},{"_id":"env_fde815a24ba03e04e82f04f655ffdd5f52992e50","color":null,"created":1580540847068,"data":{"base":"http://localhost:8000"},"dataPropertyOrder":{"&":["base"]},"isPrivate":false,"metaSortKey":1580540847068,"modified":1580540890625,"name":"Base Environment","parentId":"wrk_30de5e0761b847ac9dcff92e0168f43c","_type":"environment"},{"_id":"jar_fde815a24ba03e04e82f04f655ffdd5f52992e50","cookies":[],"created":1580540847072,"modified":1580540847072,"name":"Default Jar","parentId":"wrk_30de5e0761b847ac9dcff92e0168f43c","_type":"cookie_jar"},{"_id":"env_832c4b2d207a4056a5a817674f9b463e","color":"#00f037","created":1580540902090,"data":{"base":"http://localhost:8000","token":"{% response 'body', 'req_fe301dfaa56344c6b690c3a51e78b12f', 'b64::JC5yZXN1bHQudG9rZW4=::46b', 'never' %}"},"dataPropertyOrder":{"&":["base","token"]},"isPrivate":false,"metaSortKey":1580540902090,"modified":1580544025148,"name":"localhost","parentId":"env_fde815a24ba03e04e82f04f655ffdd5f52992e50","_type":"environment"}]}